<?xml version="1.0" encoding="windows-1252" ?>
<!DOCTYPE Association SYSTEM "jbo_03_01.dtd">
<!---->
<Association
  xmlns="http://xmlns.oracle.com/bc4j"
  Name="GlPeriodsGlBudgetStartPeriodSnoAsso"
  Version="12.1.3.10.47"
  InheritPersonalization="merge">
  <DesignTime>
    <Attr Name="_isCodegen" Value="true"/>
  </DesignTime>
  <AssociationEnd
    Name="GlPeriods"
    Cardinality="1"
    Source="true"
    Owner="erpfms.modelfms.fmseo.GlPeriods"
    LockLevel="NONE">
    <DesignTime>
      <Attr Name="_aggregation" Value="0"/>
      <Attr Name="_finderName" Value="GlPeriods"/>
      <Attr Name="_foreignKey" Value="erpfms.modelfms.fmseo.GlPeriods.PkGlPeriods"/>
      <Attr Name="_isUpdateable" Value="true"/>
    </DesignTime>
    <AttrArray Name="Attributes">
      <Item Value="erpfms.modelfms.fmseo.GlPeriods.PeriodSno"/>
    </AttrArray>
  </AssociationEnd>
  <AssociationEnd
    Name="GlBudget"
    Cardinality="-1"
    Owner="erpfms.modelfms.fmseo.GlBudget">
    <DesignTime>
      <Attr Name="_aggregation" Value="0"/>
      <Attr Name="_finderName" Value="GlBudget"/>
      <Attr Name="_foreignKey" Value="erpfms.modelfms.fmseo.GlBudget.fk_GlBudget"/>
      <Attr Name="_isUpdateable" Value="true"/>
    </DesignTime>
    <AttrArray Name="Attributes">
      <Item Value="erpfms.modelfms.fmseo.GlBudget.StartPeriodSno"/>
    </AttrArray>
  </AssociationEnd>
</Association>
